[{"article": "MadridActualizado:18/03/2016 16:54hDomino's Pizza est\u00e1 negociando con el Gobierno de Nueva Zelanda para hacer pruebas de reparto de pizza a domicilio a trav\u00e9s de robots DRU (Domino's Robotic Unit), seg\u00fan han informado medios locales.El nuevo robot DRU tiene un sistema sensorial que utiliza un l\u00e1ser para moverse alrededor de los obst\u00e1culos y llegar a su destino sin asistencia humana a una velocidad de 20 kil\u00f3metros por hora.El ministro de Transportes de Nueva Zelanda, Simon Bridges, ha indicado que el uso de estos nuevos robots por primera vez es una oportunidad \u00abinnovadora\u00bb para el pa\u00eds.Bridges ha a\u00f1adido que la nueva tecnolog\u00eda y la innovaci\u00f3n es una \u00abprioridad\u00bb para Nueva Zelanda, que en los \u00faltimos doce meses ha sido \u00abel nido\u00bb para la prueba de nuevos tipos de transporte.El a\u00f1o pasado el Gobierno ya puso en marcha un programa para realizar pruebas de veh\u00edculos a\u00e9reos no tripulados (UAV) y actualmente est\u00e1 revisando las leyes para incluir nuevas tecnolog\u00edas en los transportes.Por su parte, Domino's Pizza ha indicado en su web que DRU es el nuevo fichaje de la familia, que cuenta con \u00abelegantes formas, que combina con una personalidad amable\u00bb, y que gracias a su iluminaci\u00f3n los clientes pueden interactuar con \u00e9l.", "title": "Domino's Pizza pretende llevar a cabo sus repartos con robots", "url": "http://www.abc.es/economia/abci-dominos-pizza-pretende-llevar-cabo-repartos-robots-201603181641_noticia.html", "keywords": "reparto,robots,dominos", "date": "2016-03-18", "id": "1effcbe19fb0cbbc37e5b79ee19a7c6cc7427672", "summary": "La cadena est\u00e1 negociando con el Gobierno de Nueva Zelanda para hacer pruebas con este tipo de repartos a domicilio"}, {"article": "MadridActualizado:18/03/2016 14:53hLa ralentizaci\u00f3n del crecimiento, la ca\u00edda de los precios de las materias primas y las turbulencias en los mercados financieros est\u00e1n lanzando se\u00f1ales sobre la fragilidad de la econom\u00eda mundial. Este debilitamiento global ha llevado a los principales bancos centrales a revisar su estrategia anticrisis. A primeros de a\u00f1o, Jap\u00f3n dej\u00f3 los tipos en terreno negativo, despu\u00e9s China baj\u00f3 el coeficiente de sus reservas y, en poco m\u00e1s de una semana, cerca de media docena de supervisores han emprendido una cascada de rebajas o mantenimiento de tipos para estimular el crecimiento y combatir la deflaci\u00f3n. Reino Unido, Noruega, Suiza, Nueva Zelanda, Indonesia... las autoridades monetarias est\u00e1n sacando toda su artiller\u00eda para animar sus econom\u00edas. Todos han mantenido o bajado sus tipos en poco m\u00e1s de una semana. El \u00faltimo Noruega, que ayer los redujo al 0,5%. ( Visualiza aqu\u00ed el videoan\u00e1lisis del redactor)Antes lo hicieron el Banco Central Europeo (BCE) y la Reserva Federal (Fed) de Estados Unidos. El supervisor europeo adopt\u00f3 la semana pasada otra hist\u00f3rica bater\u00eda de medidas monetarias expansivas. Aument\u00f3 las compras de activos mensuales a 80.000 millones y redujo los tipos de inter\u00e9s oficiales hasta el \u00abgratis total\u00bb. El mi\u00e9rcoles la Fed decidi\u00f3 mantener los tipos sin cambios en la franja del 0,25% y el 0,5%. El Fondo Monetario Internacional (FMI) ya rebaj\u00f3 en enero sus c\u00e1lculos para el crecimiento de la econom\u00eda mundial del 3,6% al 3,4%. La incertidumbre planea sobre la econom\u00eda mundial y varios factores alimentan el temor. La inestabilidad del precio del petr\u00f3leo y el impacto que los bajos precios pueden tener en los pa\u00edses productores y en las compa\u00f1\u00edas petroleras; la debilidad de los mercados emergentes, el temor a que la econom\u00eda estadounidense frene en seco ante la retirada de los est\u00edmulos; el \u00abBrexit\u00bb y las consecuencias econ\u00f3micas que provocar\u00eda; o la incapacidad de la eurozona para generar un s\u00f3lido crecimiento.Emergentes. La inc\u00f3gnita de ChinaEl profesor de Esade, Pedro Aznar, cita a China como la \u00abmayor preocupaci\u00f3n de la situaci\u00f3n econ\u00f3mica global\u00bb. Por el momento, Pek\u00edn ha anunciado reformas para preparar la transici\u00f3n de un modelo basado en las exportaciones a otro con m\u00e1s impulso del consumo y la demanda interna. Pero hasta entonces, seg\u00fan sus previsiones, China crecer\u00e1 entre un 6,5 y un 7% este a\u00f1o, su peor dato desde 1990. Ello provoca que la demanda global se debilite ante el menor tir\u00f3n de la segunda potencia econ\u00f3mica mundial. Y a menor crecimiento, menores compras al exterior, lo que afecta a una paleta de pa\u00edses, que van desde Brasil a Alemania, grandes socios comerciales de China. En el caso de pa\u00edses productores de petr\u00f3leo como el gigante iberoamericano, la ca\u00edda del precio del crudo golpean con m\u00e1s fuerza a sus cuentas. Estados Unidos. Preocupaci\u00f3n por la locomotoraEE.UU. roza el pleno empleo (4,7% de tasa de paro), pero su econom\u00eda avanza m\u00e1s lentamente de lo esperado. La ca\u00edda del precio del petr\u00f3leo ha frenado inversiones en el sector energ\u00e9tico y la subida de tipos ha fortalecido el d\u00f3lar -y ha debilitado las exportaciones norteamericanas-. En este escenario, la primera potencia del mundo creci\u00f3 un 2,4% en 2015, igual que en 2014, lo que siembra dudas sobre si ser\u00e1 capaz de avanzar sin el colch\u00f3n de los est\u00edmulos monetarios. La Fed mantuvo los tipos en la franja del 0,25% y el 0,5% y, adem\u00e1s, reducir\u00e1 el ritmo de nuevas alzas. Europa. Espa\u00f1a, el motor del continente Siete a\u00f1os despu\u00e9s de que el estallido de las \u00absubprime\u00bb en EE.UU. llevara a Europa a una de las peores crisis de la historia, el motor de la zona euro no termina de arrancar. En 2015 creci\u00f3 un 1,5%, pese a que los tipos llevan a\u00f1os rozando el 0%; la inflaci\u00f3n tampoco sale de la l\u00ednea roja del 0% y la tasa de paro sigue bordeando el 20%. Espa\u00f1a creci\u00f3 el a\u00f1o pasado un 3,2%, m\u00e1s del doble que la media. Lejos est\u00e1n Alemania y Francia, con alzas del 1,7% y 1,1% e Italia, un 0,7%, que es ahora el enfermo del euro y la principal fuente de preocupaci\u00f3n. Por la enorme debilidad de su sistema financiero, con cr\u00e9ditos dudosos por importe de 350.000 millones y porque su deuda p\u00fablica sigue siendo muy elevada, en torno al 130% del PIB.Ante este escenario, las autoridades monetarias se aprestan a actuar. \u00abLa cuestion de fondo es que estas medidas monetarias compran tiempo para crear unas condiciones financieras favorables para la econom\u00eda real. Son positivas para el crecimiento, el problema es si ser\u00e1n suficientes\u00bb, sostiene Jos\u00e9 Luis Mart\u00ednez Campuzano estratega de Citi en Espa\u00f1a. Por si quedaban dudas, el propio presidente del BCE, Mario Draghi, volvi\u00f3 a pedir ayer que los gobiernos de la Eurozona act\u00faen, con \u00abm\u00e1s reformas, inversi\u00f3n p\u00fablica y bajar impuestos\u00bb. La pelota est\u00e1 en el tejado de los gobiernos.", "title": "El par\u00f3n mundial fuerza a los bancos centrales a sacar toda su artiller\u00eda", "url": "http://www.abc.es/economia/abci-paron-mundial-fuerza-bancos-centrales-sacar-toda-artilleria-201603181154_noticia.html", "keywords": "bancos,politica,centrales", "date": "2016-03-18", "id": "c945bc957a4837ada3e187306c1dc67aeb1288dc", "summary": "La bater\u00eda de est\u00edmulos del BCE ha contagiado a la Fed, que mantuvo los tipos esta semana, y al resto de autoridades monetarias del mundo"}, {"article": "MADRIDActualizado:18/03/2016 23:44hA pocos d\u00edas para que comiencen las vacaciones de Semana Santa, es la hora de ultimar los detalles para las tan esperadas vacaciones. Lo m\u00e1s probable es que muchos espa\u00f1oles opten por desplazarse en coche durante estas fiestas, lo que se traducir\u00e1 en varios millones de desplazamientos concentrados en muy pocos d\u00edas. Y el punto de reuni\u00f3n de la mayor\u00eda ser\u00e1n las gasolineras espa\u00f1olas. Para compensar el desembolso que supone rellenar el dep\u00f3sito, quiz\u00e1 sea el momento de plantearse aprovechar los descuentos, que pueden llegar a ser de hasta el 9%, ofrecidos por bancos, financieras y petroleras, se\u00f1alan desde el comparador de cuentas con descuentos en gasolina HelpMyCash.com.De hecho, cada vez son m\u00e1s los bancos que incluyen descuentos para ahorrar gasolina, la \u00fanica desventaja es que las ofertas est\u00e1n casi siempre vinculadas a una sola marca. Otro motivo m\u00e1s para comparar bien la oferta bancaria antes de decantarse por una entidad u otra.Hasta un 5% de descuento en GalpSi solemos repostar en gasolineras de la petrolera portuguesa, estamos de suerte. Hasta siete entidades ofrecen descuentos para ahorrar gasolina en Galp gracias, sobre todo, a los acuerdos firmados entre ellas y la compa\u00f1\u00eda. ING Direct devuelve un 3% del importe de los repostajes que sus clientes abonen con una tarjeta emitida por la entidad. El banco holand\u00e9s extiende la bonificaci\u00f3n cuando se realicen en las estaciones de servicio Shell. En ambos casos, sin l\u00edmite de cantidad. En el caso de Openbank, los clientes con n\u00f3mina pueden disfrutar de un 2% de descuento diario y de un 4 % los mi\u00e9rcoles con la Cuenta N\u00f3mina Open gracias al Programa de Descuentos OK. El mismo tanto por ciento aplican EVO Banco, CatalunyaCaixa y Bankia, que permiten ahorrar un 2% siempre que se pague con una de sus tarjetas.Abanca, por su parte, tambi\u00e9n ha firmado un acuerdo con la compa\u00f1\u00eda portuguesa que permite a sus clientes beneficiarse de un 2% de descuento sin l\u00edmite de importe al pagar con la tarjeta de d\u00e9bito de la entidad, un 4% al pagar con las tarjetas de cr\u00e9dito Visa y MasterCard Cl\u00e1sica y un 5% con las tarjetas Visa Oro y Visa Platinum, aunque en los dos \u00faltimos casos la bonificaci\u00f3n se aplica sobre una facturaci\u00f3n m\u00e1xima mensual de 600 euros. Por \u00faltimo, la tarjeta AvantCard, disponible sin cambiar de banco, devuelve el 2% de todo lo que se pague en las estaciones Galp adheridas a la promoci\u00f3n hasta el pr\u00f3ximo 30 de abril.50 euros de regalo para repostar en RepsolRepsol tampoco se queda atr\u00e1s en cuanto al n\u00famero de bancos que ofrecen descuentos en sus establecimientos. La Tarjeta Repsol M\u00e1xima tiene un 2% de descuento en repostajes y un 5% de ahorro en tiendas, lavados y otros servicios en las gasolineras Repsol, Campsa y Petronor. Es gratuita y no requiere cambiar de banco. Su comercializaci\u00f3n est\u00e1 mediada por bancopopular-e. Tambi\u00e9n la comercializan otras entidades como Banco Sabadell, ActivoBank, Ibercaja, Popular y Oficinadirecta, cuyos clientes pueden beneficiarse del ahorro del 2%. Sin embargo, en esos casos habr\u00e1 que consultar las condiciones espec\u00edficas de contrataci\u00f3n, ya que por lo general su solicitud est\u00e1 limitada \u00fanicamente a los que ya son clientes de estas entidades. Adem\u00e1s del descuento habitual que ofrece Openbank en Galp, la entidad premia a los nuevos clientes que contraten una Cuenta Corriente Operativa, sin n\u00f3mina, sin vinculaci\u00f3n y sin comisiones, con dos c\u00f3digos de 25 euros cada uno para repostar gratis en las estaciones de servicio Repsol, Campsa y Petronor. Para recibir los cheques regalo es necesario abrir la cuenta antes del 4 de abril y realizar un ingreso de al menos 200 euros.BBVA apuesta por recompensar a los titulares de las tarjetas Repsol M\u00e1s de cr\u00e9dito o de d\u00e9bito con un descuento de hasta 7 c\u00e9ntimos por litro. Adem\u00e1s, ofrece el descuento del 5% en tiendas, lubricantes y lavados. BP se desmarca con un imbatible 9% La tarjeta Visa BP ofrece hasta un 9% de ahorro en carburantes BP si se utiliza con pago aplazado siempre que se consuman m\u00e1s de 150 litros mensuales (en caso contrario el descuento se reduce al 8%) y, adem\u00e1s, un 3% de ahorro fuera de las estaciones de servicio BP. Por el contrario, los clientes que escojan la modalidad de pago a fin de mes, es decir sin intereses, ahorrar\u00e1n un 6% o un 5% en las gasolineras de la marca, dependiendo de si se consume m\u00e1s o menos de 150 litros mensuales y un 0,3% fuera de BP. No tiene cuotas anuales ni requiere cambiar de banco. Hay que tener presente que si utiliza el pago aplazado, se aplicar\u00e1 una TAE del 21,84%. La financiaci\u00f3n est\u00e1 mediada por Bankinter Consumer Finance. Siguiendo con las tarjetas de fidelizaci\u00f3n de las grandes petroleras, no pod\u00eda faltar en este ranking la popular Visa Cepsa Porque t\u00fa vuelves. Ofrece hasta un 6% de descuento en las estaciones de servicio de la marca adheridas a la promoci\u00f3n, correspondiente con un 3% de ahorro inmediato y un 3% extra mensual si se realiza un gasto de m\u00e1s de 300 euros fuera de las estaciones de servicio de la compa\u00f1\u00eda.", "title": "C\u00f3mo ahorrar hasta un 9% en gasolina esta Semana Santa con tu banco", "url": "http://www.abc.es/economia/abci-como-ahorrar-hasta-9-por-ciento-gasolina-esta-semana-santa-banco-201603182250_noticia.html", "keywords": "santa,gasolina,semana,ahorrar", "date": "2016-03-18", "id": "3a76a93cd832fe82de60ce66dd3dcc151fb8d452", "summary": "Las entidades ofrecen descuentos para repostar en determinados centros de servicios"}]